interlify/__init__.py
interlify/client.py
interlify-1.0.5.dist-info/METADATA
interlify-1.0.5.dist-info/WHEEL
interlify-1.0.5.dist-info/top_level.txt
interlify-1.0.5.dist-info/RECORD
