Metadata-Version: 2.2
Name: interlify
Version: 1.0.5
Summary: A Python client for the Interlify API
Home-page: https://github.com/EricZhou0815/Interlify-python-sdk
Author: Interlify
Author-email: eric.zhoul@interlify.com
Classifier: Programming Language :: Python :: 3
Classifier: License :: OSI Approved :: MIT License
Classifier: Operating System :: OS Independent
Requires-Python: >=3.6
Requires-Dist: requests
Requires-Dist: openai-agents
Dynamic: author
Dynamic: author-email
Dynamic: classifier
Dynamic: description
Dynamic: description-content-type
Dynamic: home-page
Dynamic: requires-dist
Dynamic: requires-python
Dynamic: summary
